excels_in_directory_reader/__init__.py
excels_in_directory_reader/reader.py
exceldirreader-1.0.dist-info/LICENSE
exceldirreader-1.0.dist-info/METADATA
exceldirreader-1.0.dist-info/WHEEL
exceldirreader-1.0.dist-info/top_level.txt
exceldirreader-1.0.dist-info/RECORD
