Metadata-Version: 2.1
Name: exceldirreader
Version: 1.0
Summary: Reads multiple excel files from a directory
Home-page: UNKNOWN
License: UNKNOWN
Platform: UNKNOWN
